{
  "ua": "Mozilla/5.0 (iPhone; CPU iPhone OS 13_2_3 like Mac OS X) AppleWebKit/605.1.15 (KHTML, like Gecko) Version/13.0.3 Mobile/15E148 Safari/604.1",
  "homeUrl": "http://1090ys8.com/",
  "dcVipFlag": "true",
  "pCfgJs": "http://1090ys8.com/static/js/playerconfig.js",
  "pCfgJsR": "[\\W|\\S|.]*?MacPlayerConfig.player_list[\\W|\\S|.]*?=([\\W|\\S|.]*?),MacPlayerConfig.downer_list",
  "dcShow2Vip": {},
  "dcPlayUrl": "true",
  "cateNode": "//ul[contains(@class,'type-slide')]/li/a[contains(@href, 'whole')]",
  "cateName": "/text()",
  "cateId": "/@href",
  "cateIdR": "/whole/(\\d+).html",
  "cateManual": {},
  "homeVodNode": "//div[contains(@class, 'stui-pannel__bd')]//ul[contains(@class,'stui-vodlist')]/li//a[contains(@class,'stui-vodlist__thumb')]",
  "homeVodName": "/@title",
  "homeVodId": "/@href",
  "homeVodIdR": "/show/(\\w+).html",
  "homeVodImg": "/@data-original",
  "homeVodImgR": "\\S+(http\\S+)",
  "homeVodMark": "/span[contains(@class,'pic-text')]/text()",
  "cateUrl": "http://1090ys8.com/whole/{cateId}/page/{catePg}.html",
  "cateVodNode": "//ul[contains(@class,'stui-vodlist')]//li//a[contains(@class,'stui-vodlist__thumb')]",
  "cateVodName": "/@title",
  "cateVodId": "/@href",
  "cateVodIdR": "/show/(\\w+).html",
  "cateVodImg": "/@data-original",
  "cateVodImgR": "\\S+(http\\S+)",
  "cateVodMark": "/span[contains(@class,'pic-text')]/text()",
  "dtUrl": "http://1090ys8.com/show/{vid}.html",
  "dtNode": "//div[@class='stui-content']",
  "dtName": "//div[@class='stui-content__detail']/h1/text()",
  "dtNameR": "",
  "dtImg": "//div[@class='stui-content__thumb']/a/img/@data-original",
  "dtImgR": "\\S+(http\\S+)",
	"dtYear": "//div[@class='stui-content__detail']/p[1]/text()",
	"dtYearR": "\\年份：(\\S+)",
	"dtArea": "//div[@class='stui-content__detail']/p[1]/text()",
	"dtAreaR": "\\地区：(\\S+)",
	"dtActor": "//div[@class='stui-content__detail']/p[2]/text()",
	"dtActorR": "\\主演：(\\S+)",
	"dtDirector": "//div[@class='stui-content__detail']/p[2]/text()",
	"dtDirectorR": "\\导演：(\\S+)",
  "dtDesc": "",
  "dtDescR": "",
  "dtFromNode": "//div[contains(@class,'stui-vodlist__head')]/div[contains(@class,'stui-pannel__head')]",
  "dtFromName": "/h3/text()",
  "dtFromNameR": "",
  "dtUrlNode": "//ul[contains(@class,'stui-content__playlist')]",
  "dtUrlSubNode": "/li/a",
  "dtUrlId": "/@href",
  "dtUrlIdR": "/play/(\\S+).html",
  "dtUrlName": "/text()",
  "dtUrlNameR": "",
  "playUrl": "http://1090ys8.com/play/{playUrl}.html",
  "playUa": "",
  "searchUrl": "http://1090ys8.com/index.php/ajax/suggest?mid=1&wd={wd}&limit=10",
  "scVodNode": "json:list",
  "scVodName": "name",
  "scVodId": "id",
  "scVodIdR": "",
  "scVodImg": "pic",
  "scVodMark": ""
}
